README.md
setup.py
Dome9AWSSGAnalyzer.egg-info/PKG-INFO
Dome9AWSSGAnalyzer.egg-info/SOURCES.txt
Dome9AWSSGAnalyzer.egg-info/dependency_links.txt
Dome9AWSSGAnalyzer.egg-info/requires.txt
Dome9AWSSGAnalyzer.egg-info/top_level.txt
SGAnalyzerApp/Dome9SG.py
SGAnalyzerApp/SGAnalyzerApp.py