Metadata-Version: 2.1
Name: Dome9AWSSGAnalyzer
Version: 1.0.1
Summary: Get AWS-SG Details to respond to incidents quickly.
Home-page: UNKNOWN
Author: Nitin Sharma
Author-email: ntnshrm87@gmail.com
License: MIT
Keywords: Dome9,AWS,Security Groups,Dome9v2API
Platform: UNKNOWN
Classifier: License :: OSI Approved :: MIT License
Classifier: Programming Language :: Python :: 3
Classifier: Natural Language :: English
Classifier: Intended Audience :: Developers
Classifier: Topic :: Software Development :: Libraries :: Python Modules
